8_3_priority.v
module enc_8_3_priority(
    output reg [2:0] a,
    output reg valid,
    input [7:0] d
);
    always @(*) begin
        valid = 1'b1;
        if (d[7])       a = 3'b111;
        else if (d[6])  a = 3'b110;
        else if (d[5])  a = 3'b101;
        else if (d[4])  a = 3'b100;
        else if (d[3])  a = 3'b011;
        else if (d[2])  a = 3'b010;
        else if (d[1])  a = 3'b001;
        else if (d[0])  a = 3'b000;
        else begin
            a = 3'b000;   
            valid = 1'b0;
        end
    end
endmodule

enc_8_3_prior.v
module tb_enc_8_3_priority; 
  reg [7:0] d;
  wire [2:0] a;
  wire valid;


  enc_8_3_priority uut (.d(d), .a(a), .valid(valid));

  initial begin
    $dumpfile("z21.vcd");
    $dumpvars(0, tb_enc_8_3_priority);
    
    $display("D0 D1 D2 D3 D4 D5 D6 D7 | A2 A1 A0 V");
    $monitor("%b  %b  %b  %b  %b  %b  %b  %b  |  %b  %b  %b  %b",
              d[0], d[1], d[2], d[3], d[4], d[5], d[6], d[7],
              a[2], a[1], a[0], valid);

    d = 8'b00000001; #10;
    d = 8'b0000001x; #10;
    d = 8'b000001xx; #10;
    d = 8'b00001xxx; #10;
    d = 8'b0001xxxx; #10;
    d = 8'b001xxxxx; #10;
    d = 8'b01xxxxxx; #10;
    d = 8'b1xxxxxxx; #10;
    d = 8'b00000000; #10;
    
    $finish;
  end
endmodule

z21.vcd
$date
	Sun Jun 01 00:52:14 2025
$end
$version
	Icarus Verilog
$end
$timescale
	1s
$end
$scope module tb_enc_8_3_priority $end
$var wire 3 ! a [2:0] $end
$var wire 1 " valid $end
$var reg 8 # d [7:0] $end
$scope module uut $end
$var wire 8 $ d [7:0] $end
$var reg 3 % a [2:0] $end
$var reg 1 & valid $end
$upscope $end
$upscope $end
$enddefinitions $end
#0
$dumpvars
1&
b0 %
b1 $
b1 #
1"
b0 !
$end
#10
b1 %
b1 !
b1x #
b1x $
#20
b10 %
b10 !
b1xx #
b1xx $
#30
b11 %
b11 !
b1xxx #
b1xxx $
#40
b100 %
b100 !
b1xxxx #
b1xxxx $
#50
b101 %
b101 !
b1xxxxx #
b1xxxxx $
#60
b110 %
b110 !
b1xxxxxx #
b1xxxxxx $
#70
b111 %
b111 !
b1xxxxxxx #
b1xxxxxxx $
#80
0&
0"
b0 %
b0 !
b0 #
b0 $
